usercustomize.py
usercustomize3264-1.0.dist-info/DESCRIPTION.rst
usercustomize3264-1.0.dist-info/METADATA
usercustomize3264-1.0.dist-info/RECORD
usercustomize3264-1.0.dist-info/WHEEL
usercustomize3264-1.0.dist-info/metadata.json
usercustomize3264-1.0.dist-info/top_level.txt
